ewatercycle_DA/DA.py
ewatercycle_DA/__init__.py
ewatercycle_DA/utils.py
ewatercycle_DA/data_assimilation_schemes/EnKF.py
ewatercycle_DA/data_assimilation_schemes/PF.py
ewatercycle_DA/data_assimilation_schemes/__init__.py
ewatercycle_DA/local_models/HBV.py
ewatercycle_DA/local_models/__init__.py
ewatercycle_DA/local_models/lorenz.py
ewatercycle_da-0.0.7.dist-info/METADATA
ewatercycle_da-0.0.7.dist-info/WHEEL
ewatercycle_da-0.0.7.dist-info/licenses/LICENSE.txt
ewatercycle_da-0.0.7.dist-info/RECORD
