Metadata-Version: 2.3
Name: ewatercycle-DA
Version: 0.0.7
Summary: Implementation of data assimilation for eWaterCycle
Project-URL: homepage, https://github.com/Daafip/ewatercycle-da
Author-email: David Haasnoot <davidhaasnoot@gmail.com>
License-Expression: Apache-2.0
License-File: LICENSE.txt
Keywords: data assimilation,ewatercycle,hydrology,parallelisation
Classifier: Intended Audience :: Developers
Classifier: License :: OSI Approved :: Apache Software License
Classifier: Natural Language :: English
Classifier: Operating System :: OS Independent
Classifier: Programming Language :: Python
Classifier: Programming Language :: Python :: 3 :: Only
Requires-Dist: ewatercycle
